sompy/__init__.py
sompy/codebook.py
sompy/decorators.py
sompy/neighborhood.py
sompy/normalization.py
sompy/sompy.py
sompy/visualization/__init__.py
sompy/visualization/bmuhits.py
sompy/visualization/dotmap.py
sompy/visualization/histogram.py
sompy/visualization/hitmap.py
sompy/visualization/mapview.py
sompy/visualization/plot_tools.py
sompy/visualization/plot_tools2.py
sompy/visualization/umatrix.py
sompy/visualization/view.py
sompy_package-1.0.3.dist-info/LICENSE
sompy_package-1.0.3.dist-info/METADATA
sompy_package-1.0.3.dist-info/WHEEL
sompy_package-1.0.3.dist-info/top_level.txt
sompy_package-1.0.3.dist-info/RECORD
