Metadata-Version: 2.1
Name: sompy-package
Version: 1.0.3
Summary: Self Organizing Maps Package
Author-email: Stefano Tornelli <stefano.tornelli@outlook.com>
Project-URL: Homepage, https://github.com/stefano-tornelli/SOMPY
Project-URL: Issues, https://github.com/stefano-tornelli/SOMPY/issues
Classifier: Programming Language :: Python :: 3
Classifier: License :: OSI Approved :: Apache Software License
Classifier: Operating System :: OS Independent
Requires-Python: >=3.8
License-File: LICENSE
Requires-Dist: numpy<2.0
Requires-Dist: scipy<=1.14.0
Requires-Dist: pandas<=2.2.2
Requires-Dist: scikit-learn<=1.5.1
Requires-Dist: numexpr>=2.5
Requires-Dist: scikit-image<=0.24.0
Requires-Dist: matplotlib<=3.9.1
